ems/__init__.py
ems-0.0.0.dist-info/METADATA
ems-0.0.0.dist-info/WHEEL
ems-0.0.0.dist-info/RECORD
