Metadata-Version: 2.1
Name: ems
Version: 0.0.0
Summary: Electrical Muscle Stimulation in Python
Home-page: https://github.com/Human-Computer-Integration-Lab/ems
License: MIT
Author: Philip Chmielowiec
Author-email: philipc2@uchicago.edu
Requires-Python: >=3.9
Classifier: Intended Audience :: Science/Research
Classifier: License :: OSI Approved :: MIT License
Classifier: Operating System :: OS Independent
Classifier: Programming Language :: Python
Classifier: Programming Language :: Python :: 3
Classifier: Programming Language :: Python :: 3.9
Classifier: Programming Language :: Python :: 3.10
Classifier: Programming Language :: Python :: 3.11
Classifier: Programming Language :: Python :: 3.12
Classifier: Topic :: Scientific/Engineering
Project-URL: Repository, https://github.com/Human-Computer-Integration-Lab/ems
